api/version.py
refactool-3.0.0.dist-info/LICENCE
refactool-3.0.0.dist-info/METADATA
refactool-3.0.0.dist-info/WHEEL
refactool-3.0.0.dist-info/top_level.txt
refactool-3.0.0.dist-info/RECORD
