Metadata-Version: 2.2
Name: refactool
Version: 3.0.0
Summary: Analisador de código com cache distribuído e alta performance
Author: RefacTool Team
Author-email: RefacTool Team <contato@refactool.com.br>
License: MIT
Classifier: Development Status :: 4 - Beta
Classifier: Intended Audience :: Developers
Classifier: License :: OSI Approved :: MIT License
Classifier: Natural Language :: Portuguese (Brazilian)
Classifier: Operating System :: OS Independent
Classifier: Programming Language :: Python :: 3
Classifier: Programming Language :: Python :: 3.8
Classifier: Topic :: Software Development :: Libraries :: Python Modules
Classifier: Topic :: Software Development :: Quality Assurance
Requires-Python: >=3.8
License-File: LICENCE
Dynamic: author
Dynamic: requires-python
